pklib/DataEncoder.py
pklib/DataScaling.py
pklib/DataVisualization.py
pklib/ExploreData.py
pklib/FeatureEngineering.py
pklib/InputOptimization.py
pklib/MissingValues.py
pklib/Outlier.py
pklib/Preprocessor.py
pklib/PrincipalComponentAnalysis.py
pklib/__init__.py
pklib/main.py
pklib-0.0.5.dist-info/LICENSE.txt
pklib-0.0.5.dist-info/METADATA
pklib-0.0.5.dist-info/WHEEL
pklib-0.0.5.dist-info/top_level.txt
pklib-0.0.5.dist-info/RECORD
